assets/__init__.py
assets/app_base.py
assets/config.py
automatise-0.1b21.data/scripts/MARC.py
automatise-0.1b21.data/scripts/MAT-CheckRun.py
automatise-0.1b21.data/scripts/MAT-Classifier-All.py
automatise-0.1b21.data/scripts/MAT-Classifier-MLP.py
automatise-0.1b21.data/scripts/MAT-Classifier-MLP_RF.py
automatise-0.1b21.data/scripts/MAT-ExportResults.py
automatise-0.1b21.data/scripts/MAT-MergeDatasets.py
automatise-0.1b21.data/scripts/MAT-PrintResults.py
automatise-0.1b21.data/scripts/MAT-ResultsCheck.py
automatise-0.1b21.data/scripts/MAT-ResultsTo.py
automatise-0.1b21.data/scripts/POIS-Classifier.py
automatise-0.1b21.data/scripts/POIS.py
helper/CDDiagram.py
helper/__init__.py
helper/datasets_inc.py
helper/script_inc.py
helper/io/__init__.py
helper/io/converter.py
helper/io/ts_io.py
io/__init__.py
io/converter.py
io/ts_io.py
marc/MARC.py
marc/__init__.py
marc/core/__init__.py
marc/core/logger.py
marc/core/utils/__init__.py
marc/core/utils/geohash.py
marc/core/utils/metrics.py
pois/POIS-Classifier.py
pois/POIS.py
pois/__init__.py
pois/metrics.py
pois/poifreq.py
scripts/MAT-CheckRun.py
scripts/MAT-Classifier-All.py
scripts/MAT-Classifier-MLP.py
scripts/MAT-Classifier-MLP_RF.py
scripts/MAT-ExportResults.py
scripts/MAT-MergeClasses.py
scripts/MAT-MergeDatasets.py
scripts/MAT-MoveDatasets.py
scripts/MAT-MoveletsCLS.py
scripts/MAT-PrintEnsemble.py
scripts/MAT-PrintResults.py
scripts/MAT-ResultsCheck.py
scripts/MAT-ResultsTo.py
scripts/__init__.py
automatise-0.1b21.dist-info/LICENSE
automatise-0.1b21.dist-info/METADATA
automatise-0.1b21.dist-info/WHEEL
automatise-0.1b21.dist-info/top_level.txt
automatise-0.1b21.dist-info/RECORD
